[{"id":"2f1436fd.b98e2a","type":"tab","label":"MonitorSensor","disabled":false,"info":""},{"id":"7725b780.0f776","type":"debug","z":"2f1436fd.b98e2a","name":"","active":true,"tosidebar":true,"console":true,"tostatus":false,"complete":"payload","targetType":"msg","x":320,"y":340,"wires":[]},{"id":"d3d5110b.c16e6","type":"mqtt in","z":"2f1436fd.b98e2a","name":"","topic":"hometer.iot","qos":"2","datatype":"json","broker":"1c7b0b21.750cdd","x":110,"y":200,"wires":[["7725b780.0f776","107a9023.48bb48","697aa521.2b6934","4daf7c5.4bc0804","9b7fd2b0.b1ce88","8fd79036.7b1818"]]},{"id":"9f85e668.db18d","type":"ui_gauge","z":"2f1436fd.b98e2a","name":"powerGauge","group":"36b37a1b.77dfce","order":2,"width":0,"height":0,"gtype":"gage","title":"Watts","label":"W","format":"{{value}}","min":0,"max":"200","colors":["#00b500","#e6e600","#ca3838"],"seg1":"","seg2":"","x":570,"y":360,"wires":[]},{"id":"44819a2a.3cf534","type":"ui_gauge","z":"2f1436fd.b98e2a","name":"irmsGauge","group":"36b37a1b.77dfce","order":3,"width":0,"height":0,"gtype":"gage","title":"Irms","label":"A","format":"{{value}}","min":0,"max":"20","colors":["#00b500","#e6e600","#ca3838"],"seg1":"","seg2":"","x":570,"y":280,"wires":[]},{"id":"5ae7bd89.07adec","type":"ui_gauge","z":"2f1436fd.b98e2a","name":"","group":"4c20cf00.f91568","order":4,"width":0,"height":0,"gtype":"gage","title":"hicGauge","label":"°C","format":"{{value}}","min":0,"max":"50","colors":["#00b500","#e6e600","#ca3838"],"seg1":"","seg2":"","x":560,"y":240,"wires":[]},{"id":"b505379e.cc963","type":"ui_gauge","z":"2f1436fd.b98e2a","name":"","group":"4c20cf00.f91568","order":3,"width":0,"height":0,"gtype":"gage","title":"humidityGauge","label":"%","format":"{{value}}","min":0,"max":"100","colors":["#00b5b2","#e6e600","#ca3838"],"seg1":"","seg2":"","x":580,"y":200,"wires":[]},{"id":"9b8f38bb.0851e","type":"ui_gauge","z":"2f1436fd.b98e2a","name":"","group":"4c20cf00.f91568","order":1,"width":0,"height":0,"gtype":"gage","title":"tempGauge","label":"°C","format":"{{value}}","min":0,"max":"50","colors":["#85b500","#e6e600","#ca3838"],"seg1":"","seg2":"","x":570,"y":80,"wires":[]},{"id":"107a9023.48bb48","type":"change","z":"2f1436fd.b98e2a","name":"getTemp","rules":[{"t":"set","p":"payload","pt":"msg","to":"payload.d.temp","tot":"msg"}],"action":"","property":"","from":"","to":"","reg":false,"x":300,"y":120,"wires":[["9b8f38bb.0851e","53e330cb.286558"]]},{"id":"697aa521.2b6934","type":"change","z":"2f1436fd.b98e2a","name":"getHumidity","rules":[{"t":"set","p":"payload","pt":"msg","to":"payload.d.humidity","tot":"msg"}],"action":"","property":"","from":"","to":"","reg":false,"x":310,"y":160,"wires":[["b505379e.cc963","d434b319.1e6cd8"]]},{"id":"4daf7c5.4bc0804","type":"change","z":"2f1436fd.b98e2a","name":"getHic","rules":[{"t":"set","p":"payload","pt":"msg","to":"payload.d.hic","tot":"msg"}],"action":"","property":"","from":"","to":"","reg":false,"x":290,"y":200,"wires":[["5ae7bd89.07adec","53e330cb.286558"]]},{"id":"9b7fd2b0.b1ce88","type":"change","z":"2f1436fd.b98e2a","name":"getIrms","rules":[{"t":"set","p":"payload","pt":"msg","to":"payload.d.Irms","tot":"msg"}],"action":"","property":"","from":"","to":"","reg":false,"x":300,"y":240,"wires":[["44819a2a.3cf534","db4920ba.89f088"]]},{"id":"8fd79036.7b1818","type":"change","z":"2f1436fd.b98e2a","name":"getPower","rules":[{"t":"set","p":"payload","pt":"msg","to":"payload.d.watts","tot":"msg"}],"action":"","property":"","from":"","to":"","reg":false,"x":300,"y":280,"wires":[["9f85e668.db18d","89aa9f07.969c18"]]},{"id":"53e330cb.286558","type":"ui_chart","z":"2f1436fd.b98e2a","name":"","group":"3430313c.8038b6","order":2,"width":0,"height":0,"label":"tempChart","chartType":"line","legend":"false","xformat":"HH:mm:ss","interpolate":"bezier","nodata":"","dot":true,"ymin":"","ymax":"","removeOlder":1,"removeOlderPoints":"","removeOlderUnit":"3600","cutout":0,"useOneColor":false,"useUTC":false,"colors":["#1f77b4","#aec7e8","#ff7f0e","#2ca02c","#98df8a","#d62728","#ff9896","#9467bd","#c5b0d5"],"useOldStyle":false,"outputs":1,"x":570,"y":120,"wires":[[]]},{"id":"d434b319.1e6cd8","type":"ui_chart","z":"2f1436fd.b98e2a","name":"","group":"3430313c.8038b6","order":1,"width":0,"height":0,"label":"humidityChart","chartType":"line","legend":"false","xformat":"HH:mm:ss","interpolate":"linear","nodata":"","dot":false,"ymin":"","ymax":"","removeOlder":1,"removeOlderPoints":"","removeOlderUnit":"3600","cutout":0,"useOneColor":false,"useUTC":false,"colors":["#1f77b4","#aec7e8","#ff7f0e","#2ca02c","#98df8a","#d62728","#ff9896","#9467bd","#c5b0d5"],"useOldStyle":false,"outputs":1,"x":580,"y":160,"wires":[[]]},{"id":"89aa9f07.969c18","type":"ui_chart","z":"2f1436fd.b98e2a","name":"","group":"3430313c.8038b6","order":3,"width":0,"height":0,"label":"powerChart","chartType":"line","legend":"false","xformat":"HH:mm:ss","interpolate":"linear","nodata":"","dot":false,"ymin":"","ymax":"","removeOlder":1,"removeOlderPoints":"","removeOlderUnit":"3600","cutout":0,"useOneColor":false,"useUTC":false,"colors":["#1f77b4","#aec7e8","#ff7f0e","#2ca02c","#98df8a","#d62728","#ff9896","#9467bd","#c5b0d5"],"useOldStyle":false,"outputs":1,"x":570,"y":400,"wires":[[]]},{"id":"db4920ba.89f088","type":"ui_chart","z":"2f1436fd.b98e2a","name":"","group":"36b37a1b.77dfce","order":3,"width":0,"height":0,"label":"IrmChart","chartType":"line","legend":"false","xformat":"HH:mm:ss","interpolate":"linear","nodata":"","dot":false,"ymin":"","ymax":"","removeOlder":1,"removeOlderPoints":"","removeOlderUnit":"3600","cutout":0,"useOneColor":false,"useUTC":false,"colors":["#1f77b4","#aec7e8","#ff7f0e","#2ca02c","#98df8a","#d62728","#ff9896","#9467bd","#c5b0d5"],"useOldStyle":false,"outputs":1,"x":560,"y":320,"wires":[[]]},{"id":"1c7b0b21.750cdd","type":"mqtt-broker","z":"","name":"","broker":"mqtt.eclipse.org","port":"1883","clientid":"","usetls":false,"compatmode":false,"keepalive":"60","cleansession":true,"birthTopic":"","birthQos":"0","birthPayload":"","closeTopic":"","closeQos":"0","closePayload":"","willTopic":"","willQos":"0","willPayload":""},{"id":"36b37a1b.77dfce","type":"ui_group","z":"","name":"Energia","tab":"1f83f803.120a1","order":2,"disp":true,"width":"6","collapse":false},{"id":"4c20cf00.f91568","type":"ui_group","z":"","name":"Ambiente","tab":"1f83f803.120a1","order":1,"disp":true,"width":"6","collapse":false},{"id":"3430313c.8038b6","type":"ui_group","z":"","name":"GraficosAmbiente","tab":"1f83f803.120a1","order":3,"disp":true,"width":"6","collapse":false},{"id":"1f83f803.120a1","type":"ui_tab","z":"","name":"Home Meter","icon":"dashboard","disabled":false,"hidden":false}]
